{
  "Meta": {
    "Id": "cmoxppmrc0077oackf82be8sp",
    "Name": "Ben",
    "LastUpdated": "14/June/2026"
  },
  "Build": {
    "BestWEngines": [
      {
        "Name": "Tremor Trigram Vessel",
        "Rating": "101.86%"
      },
      {
        "Name": "Cloudcleave Radiance",
        "Rating": "100.71%"
      },
      {
        "Name": "Hailstorm Shrine",
        "Rating": "100.51%"
      },
      {
        "Name": "Severed Innocence",
        "Rating": "100.37%"
      },
      {
        "Name": "Heartstring Nocturne",
        "Rating": "100.16%"
      },
      {
        "Name": "Tremor Trigram Vessel",
        "Rating": "100%"
      }
    ],
    "BestDiskSets": [
      {
        "Name": "Inferno Metal",
        "Rating": "100.00%",
        "TwoPieceOptions": [
          "Woodpecker Electro",
          "Branch & Blade Song",
          "Astral Voice, Hormone Punk",
          "Puffer Electro"
        ]
      },
      {
        "Name": "Woodpecker Electro",
        "Rating": "100.00%",
        "TwoPieceOptions": [
          "Branch & Blade Song",
          "Inferno Metal",
          "Astral Voice, Hormone Punk",
          "Puffer Electro"
        ]
      },
      {
        "Name": "Puffer Electro",
        "Rating": "100.00%",
        "TwoPieceOptions": [
          "Woodpecker Electro",
          "Branch & Blade Song",
          "Inferno Metal",
          "Astral Voice, Hormone Punk"
        ]
      }
    ],
    "MainStats": [
      {
        "Slot": "4",
        "Stats": [
          "CRIT Rate%",
          "= CRIT DMG%"
        ]
      },
      {
        "Slot": "5",
        "Stats": [
          "Fire DMG% = PEN Ratio%"
        ]
      },
      {
        "Slot": "6",
        "Stats": [
          "ATK%"
        ]
      }
    ],
    "SubStats": [
      "CRIT RATE% (aim for 70%+) = CRIT DMG%",
      "ATK%",
      "Flat PEN = Flat ATK"
    ],
    "EndgameStats": [
      "ATK: 2700 - 3600+",
      "HP: 11500+",
      "DEF: 1400 - 2600+",
      "CRIT RATE: 50% - 60%+",
      "CRIT DMG: 100% - 120%+"
    ]
  },
  "Calculation": []
}